fakebigtable/__init__.py
fakebigtable/fakebigtable.py
fakebigtable-0.1.5.dist-info/METADATA
fakebigtable-0.1.5.dist-info/WHEEL
fakebigtable-0.1.5.dist-info/RECORD
