Metadata-Version: 2.1
Name: fakebigtable
Version: 0.1.5
Summary: Fakes bigtable ops for tests
License: MIT
Author: erik aronesty
Author-email: erik@q32.com
Requires-Python: >=3.11,<4.0
Classifier: License :: OSI Approved :: MIT License
Classifier: Programming Language :: Python :: 3
Classifier: Programming Language :: Python :: 3.11
Classifier: Programming Language :: Python :: 3.12
Project-URL: homepage, https://github.com/puzzlefin/fakebigtable
